nbox/__init__.py
nbox/__main__.py
nbox/assets/job_nbx.jinja
nbox/assets/job_new.jinja
nbox/assets/job_new_readme.jinja
nbox/assets/job_serve.jinja
nbox/assets/ml.jinja
nbox/auth.py
nbox/cli.py
nbox/framework/__init__.py
nbox/framework/autogen.py
nbox/framework/ml.py
nbox/framework/model_spec_pb2.py
nbox/framework/model_spec_pb2.pyi
nbox/framework/on_functions.py
nbox/framework/on_ml.py
nbox/framework/on_operators.py
nbox/framework/protos/model_spec.proto
nbox/hyperloop/.git
nbox/hyperloop/.gitignore
nbox/hyperloop/__init__.py
nbox/hyperloop/dag_pb2.py
nbox/hyperloop/dag_pb2.pyi
nbox/hyperloop/dag_pb2_grpc.py
nbox/hyperloop/dag_pb2_grpc.pyi
nbox/hyperloop/job_pb2.py
nbox/hyperloop/job_pb2.pyi
nbox/hyperloop/job_pb2_grpc.py
nbox/hyperloop/job_pb2_grpc.pyi
nbox/hyperloop/nbox_ws_pb2.py
nbox/hyperloop/nbox_ws_pb2.pyi
nbox/hyperloop/nbox_ws_pb2_grpc.py
nbox/hyperloop/nbox_ws_pb2_grpc.pyi
nbox/hyperloop/serve_pb2.py
nbox/hyperloop/serve_pb2.pyi
nbox/hyperloop/serve_pb2_grpc.py
nbox/hyperloop/serve_pb2_grpc.pyi
nbox/init.py
nbox/instance.py
nbox/jobs.py
nbox/lib/__init__.py
nbox/lib/arch.py
nbox/lib/aws.py
nbox/lib/comms.py
nbox/lib/demo.py
nbox/lib/exceptions.py
nbox/lib/nbx_instances.py
nbox/lib/shell.py
nbox/load.py
nbox/messages.py
nbox/model.py
nbox/nbxlib/ops.py
nbox/nbxlib/tracer.py
nbox/network.py
nbox/operator.py
nbox/sub_utils/__init__.py
nbox/sub_utils/latency.py
nbox/sub_utils/pub.crt
nbox/sub_utils/ssh.py
nbox/subway.py
nbox/utils.py
nbox/version.py
nbox-0.9.12.dist-info/LICENSE
nbox-0.9.12.dist-info/WHEEL
nbox-0.9.12.dist-info/METADATA
nbox-0.9.12.dist-info/RECORD
