Metadata-Version: 2.1
Name: nbox
Version: 0.9.12
Summary: ML Inference 🥶
Home-page: https://github.com/NimbleBoxAI/nbox
License: BSD-3-Clause
Author: NBX Research
Author-email: research@nimblebox.ai
Requires-Python: >=3.6,<4.0
Classifier: License :: OSI Approved :: BSD License
Classifier: Programming Language :: Python :: 3
Classifier: Programming Language :: Python :: 3.10
Classifier: Programming Language :: Python :: 3.6
Classifier: Programming Language :: Python :: 3.7
Classifier: Programming Language :: Python :: 3.8
Classifier: Programming Language :: Python :: 3.9
Requires-Dist: Jinja2 (==3.0.3)
Requires-Dist: dill (==0.3.4)
Requires-Dist: grpcio (==1.43.0)
Requires-Dist: mypy-protobuf (==3.2.0)
Requires-Dist: protobuf (==4.21.1)
Requires-Dist: python-json-logger (==2.0.2)
Requires-Dist: randomname (>=0.1.3,<0.2.0)
Requires-Dist: requests (>=2.25.1,<3.0.0)
Requires-Dist: tabulate (==0.8.9)
Project-URL: Documentation, https://nimbleboxai.github.io/nbox/
Project-URL: Repository, https://github.com/NimbleBoxAI/nbox
